waifu2x/__init__.py
waifu2x/__main__.py
waifu2x/data_augmentation.py
waifu2x/dataset_sampler.py
waifu2x/iproc.py
waifu2x/loss/__init__.py
waifu2x/loss/clipped_weighted_huber_loss.py
waifu2x/models/resnet10/anime_style_noise0_rgb.npz
waifu2x/models/resnet10/anime_style_noise0_y.npz
waifu2x/models/resnet10/anime_style_noise1_rgb.npz
waifu2x/models/resnet10/anime_style_noise1_y.npz
waifu2x/models/resnet10/anime_style_noise2_rgb.npz
waifu2x/models/resnet10/anime_style_noise2_y.npz
waifu2x/models/resnet10/anime_style_noise3_rgb.npz
waifu2x/models/resnet10/anime_style_noise3_y.npz
waifu2x/models/resnet10/anime_style_scale_rgb.npz
waifu2x/models/resnet10/anime_style_scale_y.npz
waifu2x/models/upconv7/anime_style_noise0_scale_rgb.npz
waifu2x/models/upconv7/anime_style_noise1_scale_rgb.npz
waifu2x/models/upconv7/anime_style_noise2_scale_rgb.npz
waifu2x/models/upconv7/anime_style_noise3_scale_rgb.npz
waifu2x/models/upconv7/anime_style_scale_rgb.npz
waifu2x/models/upresnet10/anime_style_noise0_scale_rgb.npz
waifu2x/models/upresnet10/anime_style_noise1_scale_rgb.npz
waifu2x/models/upresnet10/anime_style_noise2_scale_rgb.npz
waifu2x/models/upresnet10/anime_style_noise3_scale_rgb.npz
waifu2x/models/upresnet10/anime_style_scale_rgb.npz
waifu2x/models/vgg7/anime_style_noise0_rgb.npz
waifu2x/models/vgg7/anime_style_noise0_y.npz
waifu2x/models/vgg7/anime_style_noise1_rgb.npz
waifu2x/models/vgg7/anime_style_noise1_y.npz
waifu2x/models/vgg7/anime_style_noise2_rgb.npz
waifu2x/models/vgg7/anime_style_noise2_y.npz
waifu2x/models/vgg7/anime_style_noise3_rgb.npz
waifu2x/models/vgg7/anime_style_noise3_y.npz
waifu2x/models/vgg7/anime_style_scale_rgb.npz
waifu2x/models/vgg7/anime_style_scale_y.npz
waifu2x/pairwise_transform.py
waifu2x/reconstruct.py
waifu2x/srcnn.py
waifu2x/utils.py
waifu2x-2024.dist-info/entry_points.txt
waifu2x-2024.dist-info/LICENSE.md
waifu2x-2024.dist-info/METADATA
waifu2x-2024.dist-info/WHEEL
waifu2x-2024.dist-info/RECORD
