Metadata-Version: 2.1
Name: waifu2x
Version: 2024
Summary: Chainer implementation of waifu2x
Home-page: https://github.com/FHPythonUtils/waifu2x
License: MIT
Author: FredHappyface
Requires-Python: >=3.9,<4.0
Classifier: Development Status :: 5 - Production/Stable
Classifier: Environment :: Console
Classifier: Environment :: MacOS X
Classifier: Environment :: Win32 (MS Windows)
Classifier: Intended Audience :: Developers
Classifier: Intended Audience :: Education
Classifier: License :: OSI Approved :: MIT License
Classifier: Natural Language :: English
Classifier: Operating System :: OS Independent
Classifier: Programming Language :: Python :: 3
Classifier: Programming Language :: Python :: 3.9
Classifier: Programming Language :: Python :: 3.10
Classifier: Programming Language :: Python :: 3.11
Classifier: Programming Language :: Python :: 3.12
Classifier: Programming Language :: Python :: Implementation :: CPython
Classifier: Topic :: Software Development :: Libraries :: Python Modules
Classifier: Topic :: Utilities
Requires-Dist: Pillow (>=10.2.0,<11)
Requires-Dist: Wand (>=0.6.13,<2)
Requires-Dist: chainer (>=7.8.1,<8)
Requires-Dist: numpy (>=1.26.3,<2)
Project-URL: Documentation, https://github.com/FHPythonUtils/waifu2x/blob/master/README.md
Project-URL: Repository, https://github.com/FHPythonUtils/waifu2x
